quokkaio/__init__.py
quokkaio/quokka.py
quokkaio-0.2.7.dist-info/LICENSE
quokkaio-0.2.7.dist-info/METADATA
quokkaio-0.2.7.dist-info/WHEEL
quokkaio-0.2.7.dist-info/top_level.txt
quokkaio-0.2.7.dist-info/RECORD
