Metadata-Version: 2.1
Name: quokkaio
Version: 0.2.7
Summary: API wrapper for the Quokka security software
Home-page: https://github.com/smercer-quokka/quokkaio
Author: Quokka.io
Author-email: smercer@quokka.io
License: MIT
Platform: UNKNOWN
Classifier: Intended Audience :: Developers
Classifier: License :: OSI Approved :: MIT License
Classifier: Programming Language :: Python :: 3
Classifier: Programming Language :: Python :: 3.8
Requires-Python: >=3.7
License-File: LICENSE
Requires-Dist: Requests>=2.20
